bbibbi/__init__.py
bbibbi/__init__.pyi
bbibbi/_container.py
bbibbi/_symbol.py
bbibbi/py.typed
bbibbi-0.1.4.dist-info/LICENSE
bbibbi-0.1.4.dist-info/WHEEL
bbibbi-0.1.4.dist-info/METADATA
bbibbi-0.1.4.dist-info/RECORD
